BiFuncLib/AuxFunc.py
BiFuncLib/BiclustResult.py
BiFuncLib/BsplineFunc.py
BiFuncLib/FDPlot.py
BiFuncLib/__init__.py
BiFuncLib/bcheatmap.py
BiFuncLib/bimax_biclus.py
BiFuncLib/cc_bifunc.py
BiFuncLib/cc_main_func.py
BiFuncLib/cvx_biclus.py
BiFuncLib/cvx_main_func.py
BiFuncLib/fem_bifunc.py
BiFuncLib/fem_main_func.py
BiFuncLib/lbm_bifunc.py
BiFuncLib/lbm_main_func.py
BiFuncLib/local_bifunc.py
BiFuncLib/local_main_func.py
BiFuncLib/pf_bifunc.py
BiFuncLib/pf_main_func.py
BiFuncLib/sas_bifunc.py
BiFuncLib/sas_main_func.py
BiFuncLib/simulation_data.py
BiFuncLib/sparse_bifunc.py
BiFuncLib/sparse_main_func.py
BiFuncLib/ssvd_biclus.py
BiFuncLib/ssvd_main_func.py
BiFuncLib/simulation_data/bimax_sim_data.csv
BiFuncLib/simulation_data/cc_sim_data.csv
BiFuncLib/simulation_data/cvx_sim_data.csv
BiFuncLib/simulation_data/velib_bonus.csv
BiFuncLib/simulation_data/velib_data.csv
BiFuncLib/simulation_data/velib_dates.csv
BiFuncLib/simulation_data/velib_names.csv
BiFuncLib/simulation_data/velib_position.csv
bifunclib-1.0.0.dist-info/licenses/LICENSE.txt
bifunclib-1.0.0.dist-info/METADATA
bifunclib-1.0.0.dist-info/WHEEL
bifunclib-1.0.0.dist-info/top_level.txt
bifunclib-1.0.0.dist-info/RECORD
