Metadata-Version: 2.4
Name: BiFuncLib
Version: 1.0.0
Summary: A Python library for biclustering with functional data
Home-page: https://github.com/XMU-Kuangnan-Fang-Team/BiFuncLib/
Author: Yuhao Zhong
Author-email: Barry57@163.com
License: MIT
Classifier: Development Status :: 5 - Production/Stable
Classifier: Intended Audience :: Science/Research
Classifier: License :: OSI Approved :: MIT License
License-File: LICENSE.txt
Requires-Dist: numpy<2,>=1.21.0
Requires-Dist: pandas
Requires-Dist: matplotlib
Requires-Dist: scipy
Requires-Dist: GENetLib==1.2.6
Requires-Dist: scikit-learn==1.2.2
Requires-Dist: scikit-learn-extra==0.3.0
Requires-Dist: seaborn
Requires-Dist: networkx
Dynamic: author
Dynamic: author-email
Dynamic: classifier
Dynamic: description
Dynamic: description-content-type
Dynamic: home-page
Dynamic: license
Dynamic: license-file
Dynamic: requires-dist
Dynamic: summary
